<annotation>
	<folder>my-project-name</folder>
	<filename>IMG_6989.jpeg</filename>
	<path>/my-project-name/IMG_6989.jpeg</path>
	<source>
		<database>Unspecified</database>
	</source>
	<size>
		<width>3024</width>
		<height>4032</height>
		<depth>3</depth>
	</size>
	<object>
		<name>lambo</name>
		<pose>Unspecified</pose>
		<truncated>0</truncated>
		<difficult>0</difficult>
		<bndbox>
			<xmin>419</xmin>
			<ymin>1052</ymin>
			<xmax>2510</xmax>
			<ymax>2617</ymax>
		</bndbox>
	</object>
</annotation>